VizKG/__init__.py
VizKG/visualize.py
VizKG/charts/__init__.py
VizKG/charts/areachart.py
VizKG/charts/barchart.py
VizKG/charts/boxplot.py
VizKG/charts/bubblechart.py
VizKG/charts/chart.py
VizKG/charts/densityplot.py
VizKG/charts/dimensions.py
VizKG/charts/donutchart.py
VizKG/charts/graph.py
VizKG/charts/heatmap.py
VizKG/charts/histogram.py
VizKG/charts/imagegrid.py
VizKG/charts/linechart.py
VizKG/charts/map.py
VizKG/charts/piechart.py
VizKG/charts/radarchart.py
VizKG/charts/scatterchart.py
VizKG/charts/stackedareachart.py
VizKG/charts/sunburstchart.py
VizKG/charts/table.py
VizKG/charts/timeline.py
VizKG/charts/tree.py
VizKG/charts/treemap.py
VizKG/charts/violinplot.py
VizKG/charts/wordcloud.py
VizKG/utils/__init__.py
VizKG/utils/chartdict.py
VizKG/utils/util.py
VizKG-1.0.9.dist-info/LICENSE
VizKG-1.0.9.dist-info/METADATA
VizKG-1.0.9.dist-info/WHEEL
VizKG-1.0.9.dist-info/top_level.txt
VizKG-1.0.9.dist-info/RECORD
