Metadata-Version: 2.1
Name: VizKG
Version: 1.0.9
Summary: Visualization library for SPARQL query results
Home-page: UNKNOWN
Author: Hana
License: MIT
Project-URL: Source Code, https://github.com/fadirra/vizkg
Project-URL: Demo, https://www.youtube.com/watch?v=i0dd_-PRxlI
Platform: UNKNOWN
Classifier: Programming Language :: Python :: 3
Classifier: License :: OSI Approved :: MIT License
Classifier: Operating System :: OS Independent
Requires-Python: >=3.7
Requires-Dist: pandas (>=1.0.1)
Requires-Dist: SPARQLWrapper
Requires-Dist: matplotlib
Requires-Dist: seaborn
Requires-Dist: imageio
Requires-Dist: plotly (==4.14.3)
Requires-Dist: networkx
Requires-Dist: folium
Requires-Dist: anytree
Requires-Dist: wordcloud
Requires-Dist: IPython
